Tarea2_SystemC/counter.v
`timescale 1ns / 1ns
// Verilog DUT 
module counter(
rst,   // Reset input
clk,   // Clock Input
d_out  // Counter output
);
// Port Declation
input      rst;
input      clk;
output  [31:0]  d_out;
// Internal data type
reg  [31:0]  d_out;
// Code starts here
always @ (posedge clk)
  if (rst)
  begin
    d_out <= 0;
  end
  else
  begin
    d_out <= d_out + 1;
  end

endmodule

// Testbench top level
module tb();
reg      rst;
reg      clk;
wire  [31:0]  d_out;

initial begin
 $dumpfile("verilog.vcd");
 $dumpvars(0);
 $display("[DUT Counter]: Starting sc_counter...");
 $sc_tb;// Testbench Connection
 clk = 0;
end
// Clock generator
always #1 clk = ~clk;
  
// DUT connection
counter dut (
    // Inputs
    rst,
    clk,
    // Outputs
    d_out
);

endmodule

Tarea2_SystemC/verilog.vcd
$date
	Thu May 10 20:26:33 2018
$end
$version
	Icarus Verilog
$end
$timescale
	1ns
$end
$scope module tb $end
$var wire 32 ! d_out [31:0] $end
$var reg 1 " clk $end
$var reg 1 # rst $end
$scope module dut $end
$var wire 1 $ clk $end
$var wire 1 % rst $end
$var reg 32 & d_out [31:0] $end
$upscope $end
$upscope $end
$enddefinitions $end
#0
$dumpvars
bx &
0%
0$
0#
0"
bx !
$end
#1
b0 &
b0 !
1"
1#
1%
1$
#2
0"
0$
#3
1"
1$
#4
0"
0$
#5
1"
1$
#6
0"
0$
#7
1"
1$
#8
0"
0$
#9
1"
1$
#10
0"
0$
#11
1"
1$
#12
0"
0$
#13
1"
1$
#14
0"
0$
#15
1"
1$
#16
0"
0$
#17
1"
1$
#18
0"
0$
#19
1"
1$
#20
0"
0$
#21
b1 &
b1 !
1"
0#
0%
1$
#22
0"
0$
#23
b10 &
b10 !
1"
1$
#24
0"
0$
#25
b11 &
b11 !
1"
1$
#26
0"
0$
#27
b100 &
b100 !
1"
1$
#28
0"
0$
#29
b101 &
b101 !
1"
1$
#30
0"
0$
#31
b110 &
b110 !
1"
1$
#32
0"
0$
#33
b111 &
b111 !
1"
1$
#34
0"
0$
#35
b1000 &
b1000 !
1"
1$
#36
0"
0$
#37
b1001 &
b1001 !
1"
1$
#38
0"
0$
#39
b1010 &
b1010 !
1"
1$
#40
0"
0$
#41
b1011 &
b1011 !
1"
1$
#42
0"
0$
#43
b1100 &
b1100 !
1"
1$
#44
0"
0$
#45
b1101 &
b1101 !
1"
1$
#46
0"
0$
#47
b1110 &
b1110 !
1"
1$
#48
0"
0$
#49
b1111 &
b1111 !
1"
1$
#50
0"
0$
#51
b10000 &
b10000 !
1"
1$
#52
0"
0$
#53
b10001 &
b10001 !
1"
1$
#54
0"
0$
#55
b10010 &
b10010 !
1"
1$
#56
0"
0$
#57
b10011 &
b10011 !
1"
1$
#58
0"
0$
#59
b10100 &
b10100 !
1"
1$
#60
0"
0$
#61
b10101 &
b10101 !
1"
1$
#62
0"
0$
#63
b10110 &
b10110 !
1"
1$
#64
0"
0$
#65
b10111 &
b10111 !
1"
1$
#66
0"
0$
#67
b11000 &
b11000 !
1"
1$
#68
0"
0$
#69
b11001 &
b11001 !
1"
1$
#70
0"
0$
#71
b11010 &
b11010 !
1"
1$
#72
0"
0$
#73
b11011 &
b11011 !
1"
1$
#74
0"
0$
#75
b11100 &
b11100 !
1"
1$
#76
0"
0$
#77
b11101 &
b11101 !
1"
1$
#78
0"
0$
#79
b11110 &
b11110 !
1"
1$
#80
0"
0$
#81
b11111 &
b11111 !
1"
1$
#82
0"
0$
#83
b100000 &
b100000 !
1"
1$
#84
0"
0$
#85
b100001 &
b100001 !
1"
1$
#86
0"
0$
#87
b100010 &
b100010 !
1"
1$
#88
0"
0$
#89
b100011 &
b100011 !
1"
1$
#90
0"
0$
#91
b100100 &
b100100 !
1"
1$
#92
0"
0$
#93
b100101 &
b100101 !
1"
1$
#94
0"
0$
#95
b100110 &
b100110 !
1"
1$
#96
0"
0$
#97
b100111 &
b100111 !
1"
1$
#98
0"
0$
#99
b101000 &
b101000 !
1"
1$
#100
0"
0$
#101
b101001 &
b101001 !
1"
1$
#102
0"
0$
#103
b101010 &
b101010 !
1"
1$
#104
0"
0$
#105
b101011 &
b101011 !
1"
1$
#106
0"
0$
#107
b101100 &
b101100 !
1"
1$
#108
0"
0$
#109
b101101 &
b101101 !
1"
1$
#110
0"
0$
#111
b101110 &
b101110 !
1"
1$
#112
0"
0$
#113
b101111 &
b101111 !
1"
1$
#114
0"
0$
#115
b110000 &
b110000 !
1"
1$
#116
0"
0$
#117
b110001 &
b110001 !
1"
1$
#118
0"
0$
#119
b110010 &
b110010 !
1"
1$
#120
0"
0$
#121
b110011 &
b110011 !
1"
1$
#122
0"
0$
#123
b110100 &
b110100 !
1"
1$
#124
0"
0$
#125
b110101 &
b110101 !
1"
1$
#126
0"
0$
#127
b110110 &
b110110 !
1"
1$
#128
0"
0$
#129
b110111 &
b110111 !
1"
1$
#130
0"
0$
#131
b111000 &
b111000 !
1"
1$
#132
0"
0$
#133
b111001 &
b111001 !
1"
1$
#134
0"
0$
#135
b111010 &
b111010 !
1"
1$
#136
0"
0$
#137
b111011 &
b111011 !
1"
1$
#138
0"
0$
#139
b111100 &
b111100 !
1"
1$
#140
0"
0$
#141
b111101 &
b111101 !
1"
1$
#142
0"
0$
#143
b111110 &
b111110 !
1"
1$
#144
0"
0$
#145
b111111 &
b111111 !
1"
1$
#146
0"
0$
#147
b1000000 &
b1000000 !
1"
1$
#148
0"
0$
#149
b1000001 &
b1000001 !
1"
1$
#150
0"
0$
#151
b1000010 &
b1000010 !
1"
1$
#152
0"
0$
#153
b1000011 &
b1000011 !
1"
1$
#154
0"
0$
#155
b1000100 &
b1000100 !
1"
1$
#156
0"
0$
#157
b1000101 &
b1000101 !
1"
1$
#158
0"
0$
#159
b1000110 &
b1000110 !
1"
1$
#160
0"
0$
#161
b1000111 &
b1000111 !
1"
1$
#162
0"
0$
#163
b1001000 &
b1001000 !
1"
1$
#164
0"
0$
#165
b1001001 &
b1001001 !
1"
1$
#166
0"
0$
#167
b1001010 &
b1001010 !
1"
1$
#168
0"
0$
#169
b1001011 &
b1001011 !
1"
1$
#170
0"
0$
#171
b1001100 &
b1001100 !
1"
1$
#172
0"
0$
#173
b1001101 &
b1001101 !
1"
1$
#174
0"
0$
#175
b1001110 &
b1001110 !
1"
1$
#176
0"
0$
#177
b1001111 &
b1001111 !
1"
1$
#178
0"
0$
#179
b1010000 &
b1010000 !
1"
1$
#180
0"
0$
#181
b1010001 &
b1010001 !
1"
1$
#182
0"
0$
#183
b1010010 &
b1010010 !
1"
1$
#184
0"
0$
#185
b1010011 &
b1010011 !
1"
1$
#186
0"
0$
#187
b1010100 &
b1010100 !
1"
1$
#188
0"
0$
#189
b1010101 &
b1010101 !
1"
1$
#190
0"
0$
#191
b1010110 &
b1010110 !
1"
1$
#192
0"
0$
#193
b1010111 &
b1010111 !
1"
1$
#194
0"
0$
#195
b1011000 &
b1011000 !
1"
1$
#196
0"
0$
#197
b1011001 &
b1011001 !
1"
1$
#198
0"
0$
#199
b1011010 &
b1011010 !
1"
1$
#200
0"
0$
#201
b1011011 &
b1011011 !
1"
1$
#202
0"
0$
#203
b1011100 &
b1011100 !
1"
1$
#204
0"
0$
#205
b1011101 &
b1011101 !
1"
1$
#206
0"
0$
#207
b1011110 &
b1011110 !
1"
1$
#208
0"
0$
#209
b1011111 &
b1011111 !
1"
1$
#210
0"
0$
#211
b1100000 &
b1100000 !
1"
1$
#212
0"
0$
#213
b1100001 &
b1100001 !
1"
1$
#214
0"
0$
#215
b1100010 &
b1100010 !
1"
1$
#216
0"
0$
#217
b1100011 &
b1100011 !
1"
1$
#218
0"
0$
#219
b1100100 &
b1100100 !
1"
1$
#220
0"
0$
#221
b1100101 &
b1100101 !
1"
1$
#222
0"
0$
#223
b1100110 &
b1100110 !
1"
1$
#224
0"
0$
#225
b1100111 &
b1100111 !
1"
1$
#226
0"
0$
#227
b1101000 &
b1101000 !
1"
1$
#228
0"
0$
#229
b1101001 &
b1101001 !
1"
1$
#230
0"
0$
#231
b1101010 &
b1101010 !
1"
1$
#232
0"
0$
#233
b1101011 &
b1101011 !
1"
1$
#234
0"
0$
#235
b1101100 &
b1101100 !
1"
1$
#236
0"
0$
#237
b1101101 &
b1101101 !
1"
1$
#238
0"
0$
#239
b1101110 &
b1101110 !
1"
1$
#240
0"
0$
#241
b1101111 &
b1101111 !
1"
1$
#242
0"
0$
#243
b1110000 &
b1110000 !
1"
1$
#244
0"
0$
#245
b1110001 &
b1110001 !
1"
1$
#246
0"
0$
#247
b1110010 &
b1110010 !
1"
1$
#248
0"
0$
#249
b1110011 &
b1110011 !
1"
1$
#250
0"
0$
#251
b1110100 &
b1110100 !
1"
1$
#252
0"
0$
#253
b1110101 &
b1110101 !
1"
1$
#254
0"
0$
#255
b1110110 &
b1110110 !
1"
1$
#256
0"
0$
#257
b1110111 &
b1110111 !
1"
1$
#258
0"
0$
#259
b1111000 &
b1111000 !
1"
1$
#260
0"
0$
#261
b0 &
b0 !
1"
1#
1%
1$
